LICENSE
MANIFEST.in
README.md
setup.py
tox.ini
tests/.DS_Store
tests/__init__.py
tests/test_tracestack.py
tracestack/__init__.py
tracestack/command_line.py
tracestack/console.py
tracestack/debugger.py
tracestack/decorators.py
tracestack/engines.py
tracestack/handler.py
tracestack/utils.py
tracestack.egg-info/PKG-INFO
tracestack.egg-info/SOURCES.txt
tracestack.egg-info/dependency_links.txt
tracestack.egg-info/entry_points.txt
tracestack.egg-info/top_level.txt