Metadata-Version: 1.1
Name: tracestack
Version: 0.2.4
Summary: Instantly search your Python error messages on the web.
Home-page: https://www.github.com/danrobinson/tracestack
Author: Dan Robinson
Author-email: danrobinson010@gmail.com
License: UNKNOWN
Download-URL: https://github.com/danrobinson/tracestack/tarball/0.2.4
Platform: UNKNOWN
